{
    "Users": [
	{
		"age": 77,
		"avatarUrl": "https://i.pravatar.cc/150?u=24042",
		"color": "#808080",
		"email": "xvcrj@isqpj.mt",
		"first_name": "maxime",
		"id": 1,
		"isPublic": false,
		"second_name": "nemo",
		"statusMessage": "watching netflix"
	},
	{
		"age": 48,
		"avatarUrl": "https://i.pravatar.cc/150?u=70519",
		"color": "#FF0000",
		"email": "rztfwx@zzxla.vb",
		"first_name": "libero",
		"id": 2,
		"isPublic": true,
		"second_name": "a",
		"statusMessage": "cooking"
	},
	{
		"age": 76,
		"avatarUrl": "https://i.pravatar.cc/150?u=38287",
		"color": "#0000FF",
		"email": "kqtjnbhm@vsceu.nv",
		"first_name": "dignissimos",
		"id": 3,
		"isPublic": false,
		"second_name": "distinctio",
		"statusMessage": "running"
	},
	{
		"age": 57,
		"avatarUrl": "https://i.pravatar.cc/150?u=21250",
		"color": "#000000",
		"email": "cededenc@rphvo.ya",
		"first_name": "ex",
		"id": 4,
		"isPublic": false,
		"second_name": "minima",
		"statusMessage": "cooking"
	},
	{
		"age": 47,
		"avatarUrl": "https://i.pravatar.cc/150?u=24213",
		"color": "#008080",
		"email": "bzfpclr@mzxqm.rq",
		"first_name": "accusantium",
		"id": 5,
		"isPublic": true,
		"second_name": "reiciendis",
		"statusMessage": "watching netflix"
	},
	{
		"age": 48,
		"avatarUrl": "https://i.pravatar.cc/150?u=37432",
		"color": "#000000",
		"email": "fhvlcl@mjnvv.sx",
		"first_name": "neque",
		"id": 6,
		"isPublic": false,
		"second_name": "repellat",
		"statusMessage": "running"
	},
	{
		"age": 31,
		"avatarUrl": "https://i.pravatar.cc/150?u=63152",
		"color": "#808080",
		"email": "cgenqlh@ijnvt.ry",
		"first_name": "nihil",
		"id": 7,
		"isPublic": false,
		"second_name": "repudiandae",
		"statusMessage": "watching netflix"
	},
	{
		"age": 76,
		"avatarUrl": "https://i.pravatar.cc/150?u=04261",
		"color": "#008080",
		"email": "lthhbzh@ybwzq.bx",
		"first_name": "dignissimos",
		"id": 8,
		"isPublic": false,
		"second_name": "dolorum",
		"statusMessage": "in a meeting"
	},
	{
		"age": 83,
		"avatarUrl": "https://i.pravatar.cc/150?u=24960",
		"color": "#FF00FF",
		"email": "zfqxcn@yybun.yv",
		"first_name": "sint",
		"id": 9,
		"isPublic": true,
		"second_name": "totam",
		"statusMessage": "running"
	},
	{
		"age": 69,
		"avatarUrl": "https://i.pravatar.cc/150?u=63048",
		"color": "#000000",
		"email": "cogyo@oeaeo.jf",
		"first_name": "modi",
		"id": 10,
		"isPublic": false,
		"second_name": "reiciendis",
		"statusMessage": "in a meeting"
	},
	{
		"age": 68,
		"avatarUrl": "https://i.pravatar.cc/150?u=71600",
		"color": "#808080",
		"email": "ntlfhdp@etvre.qw",
		"first_name": "maxime",
		"id": 11,
		"isPublic": true,
		"second_name": "voluptatibus",
		"statusMessage": "watching netflix"
	},
	{
		"age": 51,
		"avatarUrl": "https://i.pravatar.cc/150?u=40893",
		"color": "#00FFFF",
		"email": "vdnvm@ljmno.kv",
		"first_name": "itaque",
		"id": 12,
		"isPublic": false,
		"second_name": "sapiente",
		"statusMessage": "in a meeting"
	},
	{
		"age": 94,
		"avatarUrl": "https://i.pravatar.cc/150?u=13053",
		"color": "#808000",
		"email": "qtimucc@lggmk.om",
		"first_name": "perspiciatis",
		"id": 13,
		"isPublic": true,
		"second_name": "accusantium",
		"statusMessage": "cooking"
	},
	{
		"age": 96,
		"avatarUrl": "https://i.pravatar.cc/150?u=43540",
		"color": "#800080",
		"email": "jqytizky@qonup.hk",
		"first_name": "blanditiis",
		"id": 14,
		"isPublic": false,
		"second_name": "consectetur",
		"statusMessage": "running"
	},
	{
		"age": 93,
		"avatarUrl": "https://i.pravatar.cc/150?u=48003",
		"color": "#808080",
		"email": "hfezfiza@ptcbt.np",
		"first_name": "quia",
		"id": 15,
		"isPublic": false,
		"second_name": "ipsam",
		"statusMessage": "watching netflix"
	},
	{
		"age": 28,
		"avatarUrl": "https://i.pravatar.cc/150?u=02441",
		"color": "#FF00FF",
		"email": "wwaoi@pkcwj.sa",
		"first_name": "illum",
		"id": 16,
		"isPublic": false,
		"second_name": "doloremque",
		"statusMessage": "working from home"
	},
	{
		"age": 86,
		"avatarUrl": "https://i.pravatar.cc/150?u=19022",
		"color": "#008000",
		"email": "qvezfbzl@bhrkb.dd",
		"first_name": "quia",
		"id": 17,
		"isPublic": false,
		"second_name": "ex",
		"statusMessage": "cooking"
	},
	{
		"age": 69,
		"avatarUrl": "https://i.pravatar.cc/150?u=19181",
		"color": "#FF0000",
		"email": "fnmevho@photz.mw",
		"first_name": "culpa",
		"id": 18,
		"isPublic": true,
		"second_name": "a",
		"statusMessage": "running"
	},
	{
		"age": 28,
		"avatarUrl": "https://i.pravatar.cc/150?u=38368",
		"color": "#C0C0C0",
		"email": "ulesjvpo@dhqtm.ye",
		"first_name": "recusandae",
		"id": 19,
		"isPublic": true,
		"second_name": "reprehenderit",
		"statusMessage": "watching netflix"
	},
	{
		"age": 56,
		"avatarUrl": "https://i.pravatar.cc/150?u=83096",
		"color": "#808080",
		"email": "eosxaav@eowrp.hc",
		"first_name": "aperiam",
		"id": 20,
		"isPublic": true,
		"second_name": "hic",
		"statusMessage": "working from home"
	},
	{
		"age": 65,
		"avatarUrl": "https://i.pravatar.cc/150?u=96427",
		"color": "#00FF00",
		"email": "ztndcqv@bhgxi.zf",
		"first_name": "a",
		"id": 21,
		"isPublic": true,
		"second_name": "commodi",
		"statusMessage": "in a meeting"
	},
	{
		"age": 50,
		"avatarUrl": "https://i.pravatar.cc/150?u=91999",
		"color": "#800080",
		"email": "ivdhjh@yhglj.hy",
		"first_name": "asperiores",
		"id": 22,
		"isPublic": false,
		"second_name": "voluptatibus",
		"statusMessage": "running"
	},
	{
		"age": 46,
		"avatarUrl": "https://i.pravatar.cc/150?u=26251",
		"color": "#FF00FF",
		"email": "kxosube@tkquu.wy",
		"first_name": "repellat",
		"id": 23,
		"isPublic": false,
		"second_name": "accusamus",
		"statusMessage": "cooking"
	},
	{
		"age": 64,
		"avatarUrl": "https://i.pravatar.cc/150?u=76781",
		"color": "#008000",
		"email": "rygnbg@bmxkf.kq",
		"first_name": "a",
		"id": 24,
		"isPublic": true,
		"second_name": "a",
		"statusMessage": "working from home"
	},
	{
		"age": 95,
		"avatarUrl": "https://i.pravatar.cc/150?u=98841",
		"color": "#FF00FF",
		"email": "movquvc@rnnlh.hi",
		"first_name": "qui",
		"id": 25,
		"isPublic": false,
		"second_name": "temporibus",
		"statusMessage": "watching netflix"
	},
	{
		"age": 83,
		"avatarUrl": "https://i.pravatar.cc/150?u=33421",
		"color": "#FF0000",
		"email": "khlngxq@sndvl.aj",
		"first_name": "voluptatibus",
		"id": 26,
		"isPublic": false,
		"second_name": "explicabo",
		"statusMessage": "cooking"
	},
	{
		"age": 90,
		"avatarUrl": "https://i.pravatar.cc/150?u=02450",
		"color": "#FF00FF",
		"email": "cieox@rlyqz.sb",
		"first_name": "natus",
		"id": 27,
		"isPublic": true,
		"second_name": "facilis",
		"statusMessage": "running"
	},
	{
		"age": 68,
		"avatarUrl": "https://i.pravatar.cc/150?u=82357",
		"color": "#00FFFF",
		"email": "eruagzzb@bsgvo.lv",
		"first_name": "tempora",
		"id": 28,
		"isPublic": true,
		"second_name": "reprehenderit",
		"statusMessage": "cooking"
	},
	{
		"age": 74,
		"avatarUrl": "https://i.pravatar.cc/150?u=62175",
		"color": "#FF00FF",
		"email": "rjxvcr@dyfxk.ry",
		"first_name": "perspiciatis",
		"id": 29,
		"isPublic": true,
		"second_name": "nam",
		"statusMessage": "working from home"
	},
	{
		"age": 74,
		"avatarUrl": "https://i.pravatar.cc/150?u=77070",
		"color": "#FF0000",
		"email": "iycqoo@swfjl.ub",
		"first_name": "consequatur",
		"id": 30,
		"isPublic": true,
		"second_name": "voluptatibus",
		"statusMessage": "in a meeting"
	},
	{
		"age": 93,
		"avatarUrl": "https://i.pravatar.cc/150?u=53553",
		"color": "#0000FF",
		"email": "qxfqmow@hlibs.fb",
		"first_name": "cumque",
		"id": 31,
		"isPublic": true,
		"second_name": "nam",
		"statusMessage": "running"
	},
	{
		"age": 62,
		"avatarUrl": "https://i.pravatar.cc/150?u=56195",
		"color": "#FF0000",
		"email": "kgaldx@qmicf.lj",
		"first_name": "alias",
		"id": 32,
		"isPublic": false,
		"second_name": "eligendi",
		"statusMessage": "watching netflix"
	},
	{
		"age": 39,
		"avatarUrl": "https://i.pravatar.cc/150?u=98151",
		"color": "#000000",
		"email": "ehwemgeyp@qabtn.vf",
		"first_name": "aperiam",
		"id": 33,
		"isPublic": false,
		"second_name": "reprehenderit",
		"statusMessage": "working from home"
	},
	{
		"age": 66,
		"avatarUrl": "https://i.pravatar.cc/150?u=38867",
		"color": "#000000",
		"email": "xqbdwg@qrqrh.tb",
		"first_name": "ea",
		"id": 34,
		"isPublic": false,
		"second_name": "consequuntur",
		"statusMessage": "running"
	},
	{
		"age": 63,
		"avatarUrl": "https://i.pravatar.cc/150?u=16965",
		"color": "#800080",
		"email": "kaofc@zxsos.mx",
		"first_name": "molestiae",
		"id": 35,
		"isPublic": false,
		"second_name": "a",
		"statusMessage": "in a meeting"
	},
	{
		"age": 95,
		"avatarUrl": "https://i.pravatar.cc/150?u=69255",
		"color": "#FF0000",
		"email": "gpukgte@ayaho.hq",
		"first_name": "aut",
		"id": 36,
		"isPublic": true,
		"second_name": "deleniti",
		"statusMessage": "cooking"
	},
	{
		"age": 89,
		"avatarUrl": "https://i.pravatar.cc/150?u=57784",
		"color": "#0000FF",
		"email": "agdiqif@gaeaf.or",
		"first_name": "a",
		"id": 37,
		"isPublic": true,
		"second_name": "consequuntur",
		"statusMessage": "cooking"
	},
	{
		"age": 77,
		"avatarUrl": "https://i.pravatar.cc/150?u=16439",
		"color": "#FF00FF",
		"email": "wgsvzxy@ucupy.gj",
		"first_name": "consectetur",
		"id": 38,
		"isPublic": false,
		"second_name": "ipsum",
		"statusMessage": "in a meeting"
	},
	{
		"age": 70,
		"avatarUrl": "https://i.pravatar.cc/150?u=57918",
		"color": "#FF00FF",
		"email": "godonf@wtciy.pa",
		"first_name": "earum",
		"id": 39,
		"isPublic": false,
		"second_name": "a",
		"statusMessage": "watching netflix"
	},
	{
		"age": 84,
		"avatarUrl": "https://i.pravatar.cc/150?u=70758",
		"color": "#FF0000",
		"email": "vkest@vwonb.ne",
		"first_name": "voluptate",
		"id": 40,
		"isPublic": false,
		"second_name": "incidunt",
		"statusMessage": "in a meeting"
	},
	{
		"age": 54,
		"avatarUrl": "https://i.pravatar.cc/150?u=91969",
		"color": "#008080",
		"email": "bexbtq@xcbsk.yo",
		"first_name": "sed",
		"id": 41,
		"isPublic": true,
		"second_name": "culpa",
		"statusMessage": "working from home"
	},
	{
		"age": 73,
		"avatarUrl": "https://i.pravatar.cc/150?u=61809",
		"color": "#808080",
		"email": "ivvdego@glikr.da",
		"first_name": "a",
		"id": 42,
		"isPublic": false,
		"second_name": "consequuntur",
		"statusMessage": "working from home"
	},
	{
		"age": 39,
		"avatarUrl": "https://i.pravatar.cc/150?u=53138",
		"color": "#FF0000",
		"email": "yjece@rtnnz.vz",
		"first_name": "a",
		"id": 43,
		"isPublic": false,
		"second_name": "ullam",
		"statusMessage": "running"
	},
	{
		"age": 98,
		"avatarUrl": "https://i.pravatar.cc/150?u=63555",
		"color": "#800080",
		"email": "clnvem@omauu.qi",
		"first_name": "eos",
		"id": 44,
		"isPublic": true,
		"second_name": "reprehenderit",
		"statusMessage": "running"
	},
	{
		"age": 49,
		"avatarUrl": "https://i.pravatar.cc/150?u=11865",
		"color": "#808000",
		"email": "agvfk@pvdhs.dm",
		"first_name": "libero",
		"id": 45,
		"isPublic": true,
		"second_name": "numquam",
		"statusMessage": "running"
	},
	{
		"age": 51,
		"avatarUrl": "https://i.pravatar.cc/150?u=76873",
		"color": "#0000FF",
		"email": "qfnahjeb@myrdf.jz",
		"first_name": "quibusdam",
		"id": 46,
		"isPublic": false,
		"second_name": "dicta",
		"statusMessage": "running"
	},
	{
		"age": 82,
		"avatarUrl": "https://i.pravatar.cc/150?u=37650",
		"color": "#008080",
		"email": "xgbqx@lfiyh.al",
		"first_name": "aut",
		"id": 47,
		"isPublic": true,
		"second_name": "ea",
		"statusMessage": "cooking"
	},
	{
		"age": 78,
		"avatarUrl": "https://i.pravatar.cc/150?u=85128",
		"color": "#800080",
		"email": "mhqsy@oship.ws",
		"first_name": "ad",
		"id": 48,
		"isPublic": false,
		"second_name": "sint",
		"statusMessage": "running"
	},
	{
		"age": 50,
		"avatarUrl": "https://i.pravatar.cc/150?u=54361",
		"color": "#000000",
		"email": "fjciwjq@tkypq.ib",
		"first_name": "consectetur",
		"id": 49,
		"isPublic": false,
		"second_name": "deserunt",
		"statusMessage": "running"
	},
	{
		"age": 88,
		"avatarUrl": "https://i.pravatar.cc/150?u=29674",
		"color": "#FF00FF",
		"email": "lqllrn@aymjq.ay",
		"first_name": "quia",
		"id": 50,
		"isPublic": false,
		"second_name": "aliquam",
		"statusMessage": "working from home"
	},
	{
		"age": 41,
		"avatarUrl": "https://i.pravatar.cc/150?u=40385",
		"color": "#FF00FF",
		"email": "rqqksi@viewh.gs",
		"first_name": "id",
		"id": 51,
		"isPublic": true,
		"second_name": "a",
		"statusMessage": "running"
	},
	{
		"age": 65,
		"avatarUrl": "https://i.pravatar.cc/150?u=80076",
		"color": "#008080",
		"email": "pqufdaw@lxofk.xm",
		"first_name": "quos",
		"id": 52,
		"isPublic": true,
		"second_name": "a",
		"statusMessage": "running"
	},
	{
		"age": 23,
		"avatarUrl": "https://i.pravatar.cc/150?u=19545",
		"color": "#FF0000",
		"email": "xwvnkz@eslft.dd",
		"first_name": "voluptatibus",
		"id": 53,
		"isPublic": false,
		"second_name": "maxime",
		"statusMessage": "cooking"
	},
	{
		"age": 72,
		"avatarUrl": "https://i.pravatar.cc/150?u=73601",
		"color": "#C0C0C0",
		"email": "qpnsakb@dpalr.so",
		"first_name": "temporibus",
		"id": 54,
		"isPublic": true,
		"second_name": "deserunt",
		"statusMessage": "in a meeting"
	},
	{
		"age": 83,
		"avatarUrl": "https://i.pravatar.cc/150?u=55016",
		"color": "#800080",
		"email": "fuynywl@fdrbb.pm",
		"first_name": "esse",
		"id": 55,
		"isPublic": false,
		"second_name": "reprehenderit",
		"statusMessage": "cooking"
	},
	{
		"age": 73,
		"avatarUrl": "https://i.pravatar.cc/150?u=28783",
		"color": "#FF0000",
		"email": "vlszit@ffbcs.bt",
		"first_name": "ab",
		"id": 56,
		"isPublic": true,
		"second_name": "amet",
		"statusMessage": "cooking"
	},
	{
		"age": 69,
		"avatarUrl": "https://i.pravatar.cc/150?u=91488",
		"color": "#FF0000",
		"email": "kkfdm@qszjm.ok",
		"first_name": "a",
		"id": 57,
		"isPublic": true,
		"second_name": "dolorem",
		"statusMessage": "running"
	},
	{
		"age": 35,
		"avatarUrl": "https://i.pravatar.cc/150?u=79511",
		"color": "#800000",
		"email": "jvajdrfv@wmbwo.aw",
		"first_name": "inventore",
		"id": 58,
		"isPublic": true,
		"second_name": "quo",
		"statusMessage": "in a meeting"
	},
	{
		"age": 87,
		"avatarUrl": "https://i.pravatar.cc/150?u=96686",
		"color": "#C0C0C0",
		"email": "uqldig@wzzaz.pu",
		"first_name": "reprehenderit",
		"id": 59,
		"isPublic": true,
		"second_name": "a",
		"statusMessage": "watching netflix"
	},
	{
		"age": 96,
		"avatarUrl": "https://i.pravatar.cc/150?u=56034",
		"color": "#00FFFF",
		"email": "hyvjpyd@drhxm.xg",
		"first_name": "ipsa",
		"id": 60,
		"isPublic": false,
		"second_name": "reprehenderit",
		"statusMessage": "watching netflix"
	},
	{
		"age": 53,
		"avatarUrl": "https://i.pravatar.cc/150?u=37504",
		"color": "#C0C0C0",
		"email": "ydzwcdmu@jmqzk.tn",
		"first_name": "impedit",
		"id": 61,
		"isPublic": false,
		"second_name": "debitis",
		"statusMessage": "working from home"
	},
	{
		"age": 52,
		"avatarUrl": "https://i.pravatar.cc/150?u=91251",
		"color": "#008000",
		"email": "vkmcrzj@yhpfe.ju",
		"first_name": "at",
		"id": 62,
		"isPublic": true,
		"second_name": "ad",
		"statusMessage": "watching netflix"
	},
	{
		"age": 39,
		"avatarUrl": "https://i.pravatar.cc/150?u=75623",
		"color": "#000080",
		"email": "zfvra@iqjkn.bd",
		"first_name": "praesentium",
		"id": 63,
		"isPublic": true,
		"second_name": "excepturi",
		"statusMessage": "cooking"
	},
	{
		"age": 44,
		"avatarUrl": "https://i.pravatar.cc/150?u=65400",
		"color": "#0000FF",
		"email": "nlyddv@fywfw.bz",
		"first_name": "reiciendis",
		"id": 64,
		"isPublic": false,
		"second_name": "esse",
		"statusMessage": "running"
	},
	{
		"age": 27,
		"avatarUrl": "https://i.pravatar.cc/150?u=80448",
		"color": "#800080",
		"email": "sfbsi@jahhl.at",
		"first_name": "ex",
		"id": 65,
		"isPublic": false,
		"second_name": "perspiciatis",
		"statusMessage": "cooking"
	},
	{
		"age": 83,
		"avatarUrl": "https://i.pravatar.cc/150?u=49292",
		"color": "#000080",
		"email": "clqsf@nyfzr.su",
		"first_name": "perferendis",
		"id": 66,
		"isPublic": false,
		"second_name": "magnam",
		"statusMessage": "working from home"
	},
	{
		"age": 38,
		"avatarUrl": "https://i.pravatar.cc/150?u=49993",
		"color": "#008080",
		"email": "yicxjlxt@upnul.gb",
		"first_name": "a",
		"id": 67,
		"isPublic": false,
		"second_name": "dolore",
		"statusMessage": "running"
	},
	{
		"age": 98,
		"avatarUrl": "https://i.pravatar.cc/150?u=91937",
		"color": "#0000FF",
		"email": "ffgsgt@lotqi.rj",
		"first_name": "perspiciatis",
		"id": 68,
		"isPublic": false,
		"second_name": "enim",
		"statusMessage": "in a meeting"
	},
	{
		"age": 46,
		"avatarUrl": "https://i.pravatar.cc/150?u=52097",
		"color": "#808000",
		"email": "znxvdzaq@ljmjy.wq",
		"first_name": "a",
		"id": 69,
		"isPublic": true,
		"second_name": "voluptates",
		"statusMessage": "in a meeting"
	},
	{
		"age": 78,
		"avatarUrl": "https://i.pravatar.cc/150?u=57151",
		"color": "#000080",
		"email": "urtgdihw@eatxl.ws",
		"first_name": "voluptatibus",
		"id": 70,
		"isPublic": false,
		"second_name": "cupiditate",
		"statusMessage": "cooking"
	},
	{
		"age": 70,
		"avatarUrl": "https://i.pravatar.cc/150?u=65497",
		"color": "#FF0000",
		"email": "gnvfod@dlbku.ac",
		"first_name": "corporis",
		"id": 71,
		"isPublic": false,
		"second_name": "veniam",
		"statusMessage": "running"
	},
	{
		"age": 54,
		"avatarUrl": "https://i.pravatar.cc/150?u=77827",
		"color": "#808000",
		"email": "pydtbmv@zaulj.pf",
		"first_name": "itaque",
		"id": 72,
		"isPublic": true,
		"second_name": "eum",
		"statusMessage": "watching netflix"
	},
	{
		"age": 67,
		"avatarUrl": "https://i.pravatar.cc/150?u=73651",
		"color": "#800000",
		"email": "wakmzb@wuyfw.jh",
		"first_name": "voluptatibus",
		"id": 73,
		"isPublic": true,
		"second_name": "cupiditate",
		"statusMessage": "watching netflix"
	},
	{
		"age": 91,
		"avatarUrl": "https://i.pravatar.cc/150?u=96041",
		"color": "#00FFFF",
		"email": "pgkxng@nerxn.zw",
		"first_name": "consequuntur",
		"id": 74,
		"isPublic": true,
		"second_name": "labore",
		"statusMessage": "watching netflix"
	},
	{
		"age": 57,
		"avatarUrl": "https://i.pravatar.cc/150?u=40271",
		"color": "#000080",
		"email": "phzrksm@jnvjg.of",
		"first_name": "architecto",
		"id": 75,
		"isPublic": false,
		"second_name": "similique",
		"statusMessage": "cooking"
	},
	{
		"age": 39,
		"avatarUrl": "https://i.pravatar.cc/150?u=28084",
		"color": "#800000",
		"email": "illkmsq@tvjov.gf",
		"first_name": "reprehenderit",
		"id": 76,
		"isPublic": false,
		"second_name": "officiis",
		"statusMessage": "cooking"
	},
	{
		"age": 87,
		"avatarUrl": "https://i.pravatar.cc/150?u=20022",
		"color": "#FF0000",
		"email": "klwuhhk@qelao.ta",
		"first_name": "quos",
		"id": 77,
		"isPublic": false,
		"second_name": "accusamus",
		"statusMessage": "working from home"
	},
	{
		"age": 99,
		"avatarUrl": "https://i.pravatar.cc/150?u=39314",
		"color": "#FF00FF",
		"email": "fzhdq@masip.vp",
		"first_name": "harum",
		"id": 78,
		"isPublic": false,
		"second_name": "repudiandae",
		"statusMessage": "cooking"
	},
	{
		"age": 45,
		"avatarUrl": "https://i.pravatar.cc/150?u=40314",
		"color": "#008080",
		"email": "plngoby@bzmkx.cu",
		"first_name": "culpa",
		"id": 79,
		"isPublic": true,
		"second_name": "sed",
		"statusMessage": "watching netflix"
	},
	{
		"age": 94,
		"avatarUrl": "https://i.pravatar.cc/150?u=98047",
		"color": "#000000",
		"email": "lqbwqym@tsrkk.ha",
		"first_name": "id",
		"id": 80,
		"isPublic": true,
		"second_name": "quo",
		"statusMessage": "running"
	},
	{
		"age": 51,
		"avatarUrl": "https://i.pravatar.cc/150?u=83575",
		"color": "#800080",
		"email": "jttec@vbktg.su",
		"first_name": "a",
		"id": 81,
		"isPublic": true,
		"second_name": "dolorum",
		"statusMessage": "watching netflix"
	},
	{
		"age": 74,
		"avatarUrl": "https://i.pravatar.cc/150?u=13057",
		"color": "#0000FF",
		"email": "qchjwq@aflzs.bh",
		"first_name": "reprehenderit",
		"id": 82,
		"isPublic": true,
		"second_name": "error",
		"statusMessage": "watching netflix"
	},
	{
		"age": 33,
		"avatarUrl": "https://i.pravatar.cc/150?u=87966",
		"color": "#00FFFF",
		"email": "snxcrup@bukil.gd",
		"first_name": "dignissimos",
		"id": 83,
		"isPublic": true,
		"second_name": "quia",
		"statusMessage": "working from home"
	},
	{
		"age": 46,
		"avatarUrl": "https://i.pravatar.cc/150?u=95685",
		"color": "#008000",
		"email": "yrccf@ytvmq.al",
		"first_name": "id",
		"id": 84,
		"isPublic": false,
		"second_name": "accusantium",
		"statusMessage": "working from home"
	},
	{
		"age": 81,
		"avatarUrl": "https://i.pravatar.cc/150?u=94589",
		"color": "#000080",
		"email": "nktzeyod@omttc.wr",
		"first_name": "recusandae",
		"id": 85,
		"isPublic": false,
		"second_name": "iusto",
		"statusMessage": "in a meeting"
	},
	{
		"age": 87,
		"avatarUrl": "https://i.pravatar.cc/150?u=57852",
		"color": "#000000",
		"email": "rbjkfbvy@ousef.li",
		"first_name": "minima",
		"id": 86,
		"isPublic": true,
		"second_name": "mollitia",
		"statusMessage": "running"
	},
	{
		"age": 46,
		"avatarUrl": "https://i.pravatar.cc/150?u=18197",
		"color": "#0000FF",
		"email": "yeuof@ciczy.lr",
		"first_name": "est",
		"id": 87,
		"isPublic": false,
		"second_name": "provident",
		"statusMessage": "in a meeting"
	},
	{
		"age": 79,
		"avatarUrl": "https://i.pravatar.cc/150?u=68623",
		"color": "#800080",
		"email": "ynyxcky@jzwki.sj",
		"first_name": "voluptatibus",
		"id": 88,
		"isPublic": false,
		"second_name": "veniam",
		"statusMessage": "cooking"
	},
	{
		"age": 82,
		"avatarUrl": "https://i.pravatar.cc/150?u=25906",
		"color": "#C0C0C0",
		"email": "xkxrtj@rhdsr.iw",
		"first_name": "officiis",
		"id": 89,
		"isPublic": false,
		"second_name": "numquam",
		"statusMessage": "running"
	},
	{
		"age": 28,
		"avatarUrl": "https://i.pravatar.cc/150?u=16369",
		"color": "#800080",
		"email": "qevljjv@frjrd.xj",
		"first_name": "dignissimos",
		"id": 90,
		"isPublic": true,
		"second_name": "a",
		"statusMessage": "in a meeting"
	},
	{
		"age": 63,
		"avatarUrl": "https://i.pravatar.cc/150?u=52827",
		"color": "#000000",
		"email": "mghnw@zesfd.ho",
		"first_name": "dolore",
		"id": 91,
		"isPublic": false,
		"second_name": "possimus",
		"statusMessage": "in a meeting"
	},
	{
		"age": 45,
		"avatarUrl": "https://i.pravatar.cc/150?u=68454",
		"color": "#800000",
		"email": "uxuqxay@rfnlg.gq",
		"first_name": "reprehenderit",
		"id": 92,
		"isPublic": true,
		"second_name": "perspiciatis",
		"statusMessage": "cooking"
	},
	{
		"age": 94,
		"avatarUrl": "https://i.pravatar.cc/150?u=26451",
		"color": "#C0C0C0",
		"email": "wzbvkty@wqaxm.ll",
		"first_name": "nam",
		"id": 93,
		"isPublic": false,
		"second_name": "voluptatibus",
		"statusMessage": "cooking"
	},
	{
		"age": 91,
		"avatarUrl": "https://i.pravatar.cc/150?u=13003",
		"color": "#800080",
		"email": "ymhtedkg@toggt.vz",
		"first_name": "repellat",
		"id": 94,
		"isPublic": true,
		"second_name": "voluptas",
		"statusMessage": "in a meeting"
	},
	{
		"age": 28,
		"avatarUrl": "https://i.pravatar.cc/150?u=09101",
		"color": "#000000",
		"email": "zbnejz@kxxoq.ai",
		"first_name": "voluptatibus",
		"id": 95,
		"isPublic": false,
		"second_name": "perspiciatis",
		"statusMessage": "working from home"
	},
	{
		"age": 39,
		"avatarUrl": "https://i.pravatar.cc/150?u=50539",
		"color": "#FF0000",
		"email": "ulcud@gmspb.cv",
		"first_name": "consectetur",
		"id": 96,
		"isPublic": true,
		"second_name": "a",
		"statusMessage": "watching netflix"
	},
	{
		"age": 72,
		"avatarUrl": "https://i.pravatar.cc/150?u=71256",
		"color": "#C0C0C0",
		"email": "qkpabsr@befaw.gs",
		"first_name": "reprehenderit",
		"id": 97,
		"isPublic": true,
		"second_name": "aliquid",
		"statusMessage": "in a meeting"
	},
	{
		"age": 37,
		"avatarUrl": "https://i.pravatar.cc/150?u=24511",
		"color": "#808000",
		"email": "utdwxr@pmjhp.md",
		"first_name": "dignissimos",
		"id": 98,
		"isPublic": false,
		"second_name": "vitae",
		"statusMessage": "watching netflix"
	},
	{
		"age": 75,
		"avatarUrl": "https://i.pravatar.cc/150?u=22953",
		"color": "#0000FF",
		"email": "pacjrsot@adrzg.dk",
		"first_name": "sit",
		"id": 99,
		"isPublic": true,
		"second_name": "sed",
		"statusMessage": "in a meeting"
	},
	{
		"age": 92,
		"avatarUrl": "https://i.pravatar.cc/150?u=48606",
		"color": "#800000",
		"email": "ieolag@qplxq.th",
		"first_name": "molestiae",
		"id": 100,
		"isPublic": true,
		"second_name": "explicabo",
		"statusMessage": "in a meeting"
	}
]
}